h2ogpte_mcp_server/__init__.py
h2ogpte_mcp_server/server.py
h2ogpte_mcp_server/settings.py
h2ogpte_mcp_server/tools.py
h2ogpte_mcp_server-0.1.5.dist-info/METADATA
h2ogpte_mcp_server-0.1.5.dist-info/WHEEL
h2ogpte_mcp_server-0.1.5.dist-info/entry_points.txt
h2ogpte_mcp_server-0.1.5.dist-info/top_level.txt
h2ogpte_mcp_server-0.1.5.dist-info/RECORD
