Metadata-Version: 2.4
Name: h2ogpte-mcp-server
Version: 0.1.5
Summary: MCP API server for h2oGPTe
Author-email: "H2O.ai, Inc." <support@h2o.ai>
License-Expression: Apache-2.0
Project-URL: Source, https://github.com/h2oai/h2ogpte-mcp-server
Project-URL: Issues, https://github.com/h2oai/h2ogpte-mcp-server/issues
Project-URL: Documentation, https://github.com/h2oai/h2ogpte-mcp-server?tab=readme-ov-file
Keywords: h2ogpte,mcp,mcp-server,llm
Classifier: Development Status :: 4 - Beta
Classifier: Programming Language :: Python
Classifier: Programming Language :: Python :: 3.10
Classifier: Programming Language :: Python :: 3.11
Classifier: Programming Language :: Python :: 3.12
Classifier: Programming Language :: Python :: Implementation :: PyPy
Requires-Python: >=3.10
Requires-Dist: fastmcp==2.13.0.2
Requires-Dist: pyyaml==6.0.3
Requires-Dist: httpx==0.28.1
